{
  "chunkIndex": 4,
  "matchStartIndex": 20,
  "requestedMatchCount": 5,
  "workerIndex": 4,
  "portOffset": 12000,
  "aggregate": {
    "requestedMatchCount": 5,
    "completedMatches": 5,
    "abortedMatches": 0,
    "bossWins": 4,
    "raidWins": 1,
    "bossWinRate": 0.8,
    "raidWinRate": 0.2,
    "averageRounds": 12,
    "minRounds": 12,
    "maxRounds": 12,
    "averageRemainingRaidPlayers": 3,
    "battleMetrics": {
      "totalBattles": 60,
      "averageBossSurvivorsAtBattleEnd": 5.5,
      "averageRaidSurvivorsAtBattleEnd": 8.366666666666667,
      "bothSidesSurvivedRate": 1,
      "bossWipedRate": 0,
      "raidWipedRate": 0,
      "endReasonCounts": {
        "annihilation": 0,
        "mutual_annihilation": 0,
        "timeout_hp_lead": 1,
        "timeout_hp_tie": 0,
        "forced": 59,
        "unexpected": 0
      }
    },
    "roundHistogram": {
      "12": 5
    },
    "playerMetrics": {
      "P1": {
        "averagePlacement": 2.2,
        "firstPlaceRate": 0.2,
        "averageRemainingHp": 100,
        "averageRemainingLives": 1.8,
        "averageFinalGold": 4.6,
        "averageGoldEarned": 18.4,
        "averageGoldSpent": 98.6,
        "averagePurchaseCount": 46,
        "averageRefreshCount": 0,
        "averageSellCount": 10.8
      },
      "P2": {
        "averagePlacement": 1.6,
        "firstPlaceRate": 0.6,
        "averageRemainingHp": 100,
        "averageRemainingLives": 1.8,
        "averageFinalGold": 9.2,
        "averageGoldEarned": 24.4,
        "averageGoldSpent": 104.8,
        "averagePurchaseCount": 48.8,
        "averageRefreshCount": 0,
        "averageSellCount": 15
      },
      "P3": {
        "averagePlacement": 2.4,
        "firstPlaceRate": 0.2,
        "averageRemainingHp": 100,
        "averageRemainingLives": 2.4,
        "averageFinalGold": 0.6,
        "averageGoldEarned": 21,
        "averageGoldSpent": 99.4,
        "averagePurchaseCount": 48.8,
        "averageRefreshCount": 0.8,
        "averageSellCount": 12.4
      },
      "P4": {
        "averagePlacement": 3.8,
        "firstPlaceRate": 0,
        "averageRemainingHp": 100,
        "averageRemainingLives": 3,
        "averageFinalGold": 2.2,
        "averageGoldEarned": 20.4,
        "averageGoldSpent": 91.4,
        "averagePurchaseCount": 42.6,
        "averageRefreshCount": 0,
        "averageSellCount": 13.2
      }
    },
    "bossBattleUnitMetrics": [
      {
        "unitId": "patchouli",
        "unitType": "patchouli",
        "unitName": "パチュリー・ノーレッジ",
        "battleAppearances": 38,
        "matchesPresent": 5,
        "averageStarLevel": 1.236842105263158,
        "averageDamagePerBattle": 811.3157894736842,
        "averageDamagePerMatch": 6166,
        "activeBattleRate": 1,
        "averageAttackCountPerBattle": 2.026315789473684,
        "averageHitCountPerBattle": 4.2894736842105265,
        "averageDamageTakenPerBattle": 170.6315789473684,
        "averageFirstAttackMs": 0,
        "averageLifetimeMs": 2136.0762763932057,
        "zeroDamageBattleRate": 0,
        "survivalRate": 1,
        "ownerWinRate": 0,
        "adoptionRate": 1
      },
      {
        "unitId": "sakuya",
        "unitType": "sakuya",
        "unitName": "十六夜咲夜",
        "battleAppearances": 16,
        "matchesPresent": 5,
        "averageStarLevel": 1.1875,
        "averageDamagePerBattle": 560.8125,
        "averageDamagePerMatch": 1794.6,
        "activeBattleRate": 1,
        "averageAttackCountPerBattle": 2.8125,
        "averageHitCountPerBattle": 3.9375,
        "averageDamageTakenPerBattle": 176,
        "averageFirstAttackMs": 652.1739130434781,
        "averageLifetimeMs": 2652.5446302923087,
        "zeroDamageBattleRate": 0,
        "survivalRate": 1,
        "ownerWinRate": 0,
        "adoptionRate": 1
      },
      {
        "unitId": "remilia",
        "unitType": "remilia",
        "unitName": "レミリア",
        "battleAppearances": 60,
        "matchesPresent": 5,
        "averageStarLevel": 1,
        "averageDamagePerBattle": 84.35,
        "averageDamagePerMatch": 1012.2,
        "activeBattleRate": 0.9166666666666666,
        "averageAttackCountPerBattle": 1.9166666666666667,
        "averageHitCountPerBattle": 1.9166666666666667,
        "averageDamageTakenPerBattle": 248.53333333333333,
        "averageFirstAttackMs": 159.4896331738437,
        "averageLifetimeMs": 2729.2626806171697,
        "zeroDamageBattleRate": 0.08333333333333333,
        "survivalRate": 0.95,
        "ownerWinRate": 0,
        "adoptionRate": 1
      },
      {
        "unitId": "yoshika",
        "unitType": "yoshika",
        "unitName": "宮古芳香",
        "battleAppearances": 50,
        "matchesPresent": 5,
        "averageStarLevel": 1.66,
        "averageDamagePerBattle": 99.5,
        "averageDamagePerMatch": 995,
        "activeBattleRate": 1,
        "averageAttackCountPerBattle": 2.94,
        "averageHitCountPerBattle": 2.94,
        "averageDamageTakenPerBattle": 404.08,
        "averageFirstAttackMs": 15,
        "averageLifetimeMs": 2738.880177270269,
        "zeroDamageBattleRate": 0,
        "survivalRate": 0.62,
        "ownerWinRate": 0,
        "adoptionRate": 1
      },
      {
        "unitId": "rin",
        "unitType": "rin",
        "unitName": "火焔猫燐",
        "battleAppearances": 48,
        "matchesPresent": 5,
        "averageStarLevel": 1.5625,
        "averageDamagePerBattle": 85.70833333333333,
        "averageDamagePerMatch": 822.8,
        "activeBattleRate": 1,
        "averageAttackCountPerBattle": 2.7708333333333335,
        "averageHitCountPerBattle": 2.7708333333333335,
        "averageDamageTakenPerBattle": 486.5,
        "averageFirstAttackMs": 10.416666666666666,
        "averageLifetimeMs": 2736.0371181965597,
        "zeroDamageBattleRate": 0,
        "survivalRate": 0.5625,
        "ownerWinRate": 0,
        "adoptionRate": 1
      },
      {
        "unitId": "meiling",
        "unitType": "meiling",
        "unitName": "紅美鈴",
        "battleAppearances": 22,
        "matchesPresent": 5,
        "averageStarLevel": 1.0909090909090908,
        "averageDamagePerBattle": 144.22727272727272,
        "averageDamagePerMatch": 634.6,
        "activeBattleRate": 1,
        "averageAttackCountPerBattle": 3.1363636363636362,
        "averageHitCountPerBattle": 3.1363636363636362,
        "averageDamageTakenPerBattle": 352.1363636363636,
        "averageFirstAttackMs": 11.363636363636363,
        "averageLifetimeMs": 3215.720999143459,
        "zeroDamageBattleRate": 0,
        "survivalRate": 1,
        "ownerWinRate": 0,
        "adoptionRate": 1
      },
      {
        "unitId": "nazrin",
        "unitType": "nazrin",
        "unitName": "ナズーリン",
        "battleAppearances": 39,
        "matchesPresent": 4,
        "averageStarLevel": 1.2307692307692308,
        "averageDamagePerBattle": 155.12820512820514,
        "averageDamagePerMatch": 1210,
        "activeBattleRate": 1,
        "averageAttackCountPerBattle": 2.769230769230769,
        "averageHitCountPerBattle": 3.3076923076923075,
        "averageDamageTakenPerBattle": 180.33333333333334,
        "averageFirstAttackMs": 0,
        "averageLifetimeMs": 2409.6912146447744,
        "zeroDamageBattleRate": 0,
        "survivalRate": 0.8974358974358975,
        "ownerWinRate": 0,
        "adoptionRate": 0.8
      },
      {
        "unitId": "murasa",
        "unitType": "murasa",
        "unitName": "村紗水蜜",
        "battleAppearances": 6,
        "matchesPresent": 4,
        "averageStarLevel": 1,
        "averageDamagePerBattle": 790.5,
        "averageDamagePerMatch": 948.6,
        "activeBattleRate": 1,
        "averageAttackCountPerBattle": 2.8333333333333335,
        "averageHitCountPerBattle": 8.833333333333334,
        "averageDamageTakenPerBattle": 82,
        "averageFirstAttackMs": 0,
        "averageLifetimeMs": 2500.2334267040146,
        "zeroDamageBattleRate": 0,
        "survivalRate": 1,
        "ownerWinRate": 0,
        "adoptionRate": 0.8
      },
      {
        "unitId": "wakasagihime",
        "unitType": "wakasagihime",
        "unitName": "わかさぎ姫",
        "battleAppearances": 25,
        "matchesPresent": 4,
        "averageStarLevel": 1.12,
        "averageDamagePerBattle": 144.88,
        "averageDamagePerMatch": 724.4,
        "activeBattleRate": 1,
        "averageAttackCountPerBattle": 2.44,
        "averageHitCountPerBattle": 2.8,
        "averageDamageTakenPerBattle": 217.64,
        "averageFirstAttackMs": 0,
        "averageLifetimeMs": 1814.2769133171612,
        "zeroDamageBattleRate": 0,
        "survivalRate": 0.88,
        "ownerWinRate": 0,
        "adoptionRate": 0.8
      },
      {
        "unitId": "byakuren",
        "unitType": "byakuren",
        "unitName": "聖白蓮",
        "battleAppearances": 9,
        "matchesPresent": 4,
        "averageStarLevel": 1,
        "averageDamagePerBattle": 364.22222222222223,
        "averageDamagePerMatch": 655.6,
        "activeBattleRate": 1,
        "averageAttackCountPerBattle": 2.888888888888889,
        "averageHitCountPerBattle": 2.888888888888889,
        "averageDamageTakenPerBattle": 502.8888888888889,
        "averageFirstAttackMs": 27.77777777777778,
        "averageLifetimeMs": 2585.23996165895,
        "zeroDamageBattleRate": 0,
        "survivalRate": 1,
        "ownerWinRate": 0,
        "adoptionRate": 0.8
      },
      {
        "unitId": "megumu",
        "unitType": "megumu",
        "unitName": "飯綱丸龍",
        "battleAppearances": 8,
        "matchesPresent": 4,
        "averageStarLevel": 1,
        "averageDamagePerBattle": 313,
        "averageDamagePerMatch": 500.8,
        "activeBattleRate": 1,
        "averageAttackCountPerBattle": 2.875,
        "averageHitCountPerBattle": 3.5,
        "averageDamageTakenPerBattle": 215.625,
        "averageFirstAttackMs": 0,
        "averageLifetimeMs": 1998.196248196248,
        "zeroDamageBattleRate": 0,
        "survivalRate": 1,
        "ownerWinRate": 0,
        "adoptionRate": 0.8
      },
      {
        "unitId": "hecatia",
        "unitType": "hecatia",
        "unitName": "ヘカーティア・ラピスラズリ",
        "battleAppearances": 6,
        "matchesPresent": 3,
        "averageStarLevel": 1,
        "averageDamagePerBattle": 1336.5,
        "averageDamagePerMatch": 1603.8,
        "activeBattleRate": 1,
        "averageAttackCountPerBattle": 2.8333333333333335,
        "averageHitCountPerBattle": 8.666666666666666,
        "averageDamageTakenPerBattle": 123,
        "averageFirstAttackMs": 0,
        "averageLifetimeMs": 2522.7939128867924,
        "zeroDamageBattleRate": 0,
        "survivalRate": 1,
        "ownerWinRate": 0,
        "adoptionRate": 0.6
      },
      {
        "unitId": "shou",
        "unitType": "shou",
        "unitName": "寅丸星",
        "battleAppearances": 6,
        "matchesPresent": 3,
        "averageStarLevel": 1,
        "averageDamagePerBattle": 780.3333333333334,
        "averageDamagePerMatch": 936.4,
        "activeBattleRate": 1,
        "averageAttackCountPerBattle": 2.6666666666666665,
        "averageHitCountPerBattle": 7.166666666666667,
        "averageDamageTakenPerBattle": 170.33333333333334,
        "averageFirstAttackMs": 0,
        "averageLifetimeMs": 2121.166887807755,
        "zeroDamageBattleRate": 0,
        "survivalRate": 1,
        "ownerWinRate": 0,
        "adoptionRate": 0.6
      },
      {
        "unitId": "momoyo",
        "unitType": "momoyo",
        "unitName": "姫虫百々世",
        "battleAppearances": 9,
        "matchesPresent": 3,
        "averageStarLevel": 1.1111111111111112,
        "averageDamagePerBattle": 179,
        "averageDamagePerMatch": 322.2,
        "activeBattleRate": 1,
        "averageAttackCountPerBattle": 6,
        "averageHitCountPerBattle": 6,
        "averageDamageTakenPerBattle": 420.77777777777777,
        "averageFirstAttackMs": 0,
        "averageLifetimeMs": 6020.734024603993,
        "zeroDamageBattleRate": 0,
        "survivalRate": 0.6666666666666666,
        "ownerWinRate": 0,
        "adoptionRate": 0.6
      },
      {
        "unitId": "ichirin",
        "unitType": "ichirin",
        "unitName": "雲居一輪＆雲山",
        "battleAppearances": 9,
        "matchesPresent": 3,
        "averageStarLevel": 1,
        "averageDamagePerBattle": 155.88888888888889,
        "averageDamagePerMatch": 280.6,
        "activeBattleRate": 1,
        "averageAttackCountPerBattle": 5.555555555555555,
        "averageHitCountPerBattle": 5.555555555555555,
        "averageDamageTakenPerBattle": 394,
        "averageFirstAttackMs": 0,
        "averageLifetimeMs": 5571.952013128484,
        "zeroDamageBattleRate": 0,
        "survivalRate": 1,
        "ownerWinRate": 0,
        "adoptionRate": 0.6
      },
      {
        "unitId": "clownpiece",
        "unitType": "clownpiece",
        "unitName": "クラウンピース",
        "battleAppearances": 17,
        "matchesPresent": 2,
        "averageStarLevel": 1.1764705882352942,
        "averageDamagePerBattle": 308.52941176470586,
        "averageDamagePerMatch": 1049,
        "activeBattleRate": 1,
        "averageAttackCountPerBattle": 5.0588235294117645,
        "averageHitCountPerBattle": 6.411764705882353,
        "averageDamageTakenPerBattle": 178.8235294117647,
        "averageFirstAttackMs": 0,
        "averageLifetimeMs": 4050.5141168954683,
        "zeroDamageBattleRate": 0,
        "survivalRate": 1,
        "ownerWinRate": 0,
        "adoptionRate": 0.4
      },
      {
        "unitId": "chimata",
        "unitType": "chimata",
        "unitName": "天弓千亦",
        "battleAppearances": 3,
        "matchesPresent": 2,
        "averageStarLevel": 1,
        "averageDamagePerBattle": 576.3333333333334,
        "averageDamagePerMatch": 345.8,
        "activeBattleRate": 1,
        "averageAttackCountPerBattle": 2.3333333333333335,
        "averageHitCountPerBattle": 5.333333333333333,
        "averageDamageTakenPerBattle": 468.6666666666667,
        "averageFirstAttackMs": 0,
        "averageLifetimeMs": 1829.3650793650793,
        "zeroDamageBattleRate": 0,
        "survivalRate": 0.6666666666666666,
        "ownerWinRate": 0,
        "adoptionRate": 0.4
      },
      {
        "unitId": "seiga",
        "unitType": "seiga",
        "unitName": "霍青娥",
        "battleAppearances": 4,
        "matchesPresent": 2,
        "averageStarLevel": 1,
        "averageDamagePerBattle": 419.5,
        "averageDamagePerMatch": 335.6,
        "activeBattleRate": 1,
        "averageAttackCountPerBattle": 2.25,
        "averageHitCountPerBattle": 3.25,
        "averageDamageTakenPerBattle": 439,
        "averageFirstAttackMs": 0,
        "averageLifetimeMs": 1276.7857142857142,
        "zeroDamageBattleRate": 0,
        "survivalRate": 0.75,
        "ownerWinRate": 0,
        "adoptionRate": 0.4
      },
      {
        "unitId": "satori",
        "unitType": "satori",
        "unitName": "古明地さとり",
        "battleAppearances": 4,
        "matchesPresent": 2,
        "averageStarLevel": 1,
        "averageDamagePerBattle": 404,
        "averageDamagePerMatch": 323.2,
        "activeBattleRate": 1,
        "averageAttackCountPerBattle": 2.25,
        "averageHitCountPerBattle": 4.5,
        "averageDamageTakenPerBattle": 246,
        "averageFirstAttackMs": 0,
        "averageLifetimeMs": 1910.1307189542486,
        "zeroDamageBattleRate": 0,
        "survivalRate": 1,
        "ownerWinRate": 0,
        "adoptionRate": 0.4
      },
      {
        "unitId": "sekibanki",
        "unitType": "sekibanki",
        "unitName": "赤蛮奇",
        "battleAppearances": 4,
        "matchesPresent": 2,
        "averageStarLevel": 1,
        "averageDamagePerBattle": 345,
        "averageDamagePerMatch": 276,
        "activeBattleRate": 1,
        "averageAttackCountPerBattle": 2.25,
        "averageHitCountPerBattle": 3.25,
        "averageDamageTakenPerBattle": 422,
        "averageFirstAttackMs": 0,
        "averageLifetimeMs": 1452.3809523809523,
        "zeroDamageBattleRate": 0,
        "survivalRate": 0.5,
        "ownerWinRate": 0,
        "adoptionRate": 0.4
      },
      {
        "unitId": "tsukasa",
        "unitType": "tsukasa",
        "unitName": "菅牧典",
        "battleAppearances": 3,
        "matchesPresent": 2,
        "averageStarLevel": 1,
        "averageDamagePerBattle": 402.3333333333333,
        "averageDamagePerMatch": 241.4,
        "activeBattleRate": 1,
        "averageAttackCountPerBattle": 2.6666666666666665,
        "averageHitCountPerBattle": 5.666666666666667,
        "averageDamageTakenPerBattle": 164,
        "averageFirstAttackMs": 0,
        "averageLifetimeMs": 2136.3636363636365,
        "zeroDamageBattleRate": 0,
        "survivalRate": 1,
        "ownerWinRate": 0,
        "adoptionRate": 0.4
      },
      {
        "unitId": "zanmu",
        "unitType": "zanmu",
        "unitName": "日白残無",
        "battleAppearances": 1,
        "matchesPresent": 1,
        "averageStarLevel": 1,
        "averageDamagePerBattle": 1820,
        "averageDamagePerMatch": 364,
        "activeBattleRate": 1,
        "averageAttackCountPerBattle": 3,
        "averageHitCountPerBattle": 12,
        "averageDamageTakenPerBattle": 504,
        "averageFirstAttackMs": 0,
        "averageLifetimeMs": 3333.333333333333,
        "zeroDamageBattleRate": 0,
        "survivalRate": 1,
        "ownerWinRate": 0,
        "adoptionRate": 0.2
      },
      {
        "unitId": "koishi",
        "unitType": "koishi",
        "unitName": "古明地こいし",
        "battleAppearances": 1,
        "matchesPresent": 1,
        "averageStarLevel": 1,
        "averageDamagePerBattle": 428,
        "averageDamagePerMatch": 85.6,
        "activeBattleRate": 1,
        "averageAttackCountPerBattle": 3,
        "averageHitCountPerBattle": 4,
        "averageDamageTakenPerBattle": 631,
        "averageFirstAttackMs": 0,
        "averageLifetimeMs": 2105.263157894737,
        "zeroDamageBattleRate": 0,
        "survivalRate": 0,
        "ownerWinRate": 0,
        "adoptionRate": 0.2
      },
      {
        "unitId": "kagerou",
        "unitType": "kagerou",
        "unitName": "今泉影狼",
        "battleAppearances": 1,
        "matchesPresent": 1,
        "averageStarLevel": 1,
        "averageDamagePerBattle": 121,
        "averageDamagePerMatch": 24.2,
        "activeBattleRate": 1,
        "averageAttackCountPerBattle": 2,
        "averageHitCountPerBattle": 2,
        "averageDamageTakenPerBattle": 746,
        "averageFirstAttackMs": 0,
        "averageLifetimeMs": 2000,
        "zeroDamageBattleRate": 0,
        "survivalRate": 0,
        "ownerWinRate": 0,
        "adoptionRate": 0.2
      }
    ],
    "raidBattleUnitMetrics": [
      {
        "unitId": "yoshika",
        "unitType": "yoshika",
        "unitName": "宮古芳香",
        "battleAppearances": 102,
        "matchesPresent": 5,
        "averageStarLevel": 1.9215686274509804,
        "averageDamagePerBattle": 142.1764705882353,
        "averageDamagePerMatch": 2900.4,
        "activeBattleRate": 0.9019607843137255,
        "averageAttackCountPerBattle": 2.4019607843137254,
        "averageHitCountPerBattle": 2.4019607843137254,
        "averageDamageTakenPerBattle": 262.921568627451,
        "averageFirstAttackMs": 392.512077294686,
        "averageLifetimeMs": 2703.078197032731,
        "zeroDamageBattleRate": 0.09803921568627451,
        "survivalRate": 0.9313725490196079,
        "ownerWinRate": 0.39215686274509803,
        "adoptionRate": 1,
        "subUnitBattleAppearances": 102,
        "subUnitMatchesPresent": 5,
        "subUnitAdoptionRate": 1
      },
      {
        "unitId": "rin",
        "unitType": "rin",
        "unitName": "火焔猫燐",
        "battleAppearances": 91,
        "matchesPresent": 5,
        "averageStarLevel": 1.8021978021978022,
        "averageDamagePerBattle": 129.46153846153845,
        "averageDamagePerMatch": 2356.2,
        "activeBattleRate": 0.8351648351648352,
        "averageAttackCountPerBattle": 2.3736263736263736,
        "averageHitCountPerBattle": 2.3736263736263736,
        "averageDamageTakenPerBattle": 246.8131868131868,
        "averageFirstAttackMs": 515.4798761609907,
        "averageLifetimeMs": 2909.545051051312,
        "zeroDamageBattleRate": 0.16483516483516483,
        "survivalRate": 0.967032967032967,
        "ownerWinRate": 0.4175824175824176,
        "adoptionRate": 1,
        "subUnitBattleAppearances": 88,
        "subUnitMatchesPresent": 5,
        "subUnitAdoptionRate": 1
      },
      {
        "unitId": "kagerou",
        "unitType": "kagerou",
        "unitName": "今泉影狼",
        "battleAppearances": 39,
        "matchesPresent": 5,
        "averageStarLevel": 1.0769230769230769,
        "averageDamagePerBattle": 121.25641025641026,
        "averageDamagePerMatch": 945.8,
        "activeBattleRate": 1,
        "averageAttackCountPerBattle": 3,
        "averageHitCountPerBattle": 3,
        "averageDamageTakenPerBattle": 321.1025641025641,
        "averageFirstAttackMs": 160.25641025641025,
        "averageLifetimeMs": 2837.5796292070345,
        "zeroDamageBattleRate": 0,
        "survivalRate": 0.8974358974358975,
        "ownerWinRate": 0.10256410256410256,
        "adoptionRate": 1,
        "subUnitBattleAppearances": 39,
        "subUnitMatchesPresent": 5,
        "subUnitAdoptionRate": 1
      },
      {
        "unitId": "momoyo",
        "unitType": "momoyo",
        "unitName": "姫虫百々世",
        "battleAppearances": 34,
        "matchesPresent": 5,
        "averageStarLevel": 1.0294117647058822,
        "averageDamagePerBattle": 109.73529411764706,
        "averageDamagePerMatch": 746.2,
        "activeBattleRate": 0.9411764705882353,
        "averageAttackCountPerBattle": 2.2941176470588234,
        "averageHitCountPerBattle": 2.2941176470588234,
        "averageDamageTakenPerBattle": 401.3529411764706,
        "averageFirstAttackMs": 304.6875,
        "averageLifetimeMs": 2377.298588480127,
        "zeroDamageBattleRate": 0.058823529411764705,
        "survivalRate": 0.7647058823529411,
        "ownerWinRate": 0.3235294117647059,
        "adoptionRate": 1,
        "subUnitBattleAppearances": 34,
        "subUnitMatchesPresent": 5,
        "subUnitAdoptionRate": 1
      },
      {
        "unitId": "keiki",
        "unitType": "keiki",
        "unitName": "袿姫",
        "battleAppearances": 60,
        "matchesPresent": 5,
        "averageStarLevel": 1,
        "averageDamagePerBattle": 2.216666666666667,
        "averageDamagePerMatch": 26.6,
        "activeBattleRate": 0.08333333333333333,
        "averageAttackCountPerBattle": 0.11666666666666667,
        "averageHitCountPerBattle": 0.11666666666666667,
        "averageDamageTakenPerBattle": 72.35,
        "averageFirstAttackMs": 5650,
        "averageLifetimeMs": 2729.2626806171697,
        "zeroDamageBattleRate": 0.9166666666666666,
        "survivalRate": 1,
        "ownerWinRate": 0,
        "adoptionRate": 1,
        "subUnitBattleAppearances": 0,
        "subUnitMatchesPresent": 0,
        "subUnitAdoptionRate": 0
      },
      {
        "unitId": "seiga",
        "unitType": "seiga",
        "unitName": "霍青娥",
        "battleAppearances": 20,
        "matchesPresent": 4,
        "averageStarLevel": 1,
        "averageDamagePerBattle": 234.05,
        "averageDamagePerMatch": 936.2,
        "activeBattleRate": 1,
        "averageAttackCountPerBattle": 1.9,
        "averageHitCountPerBattle": 2.5,
        "averageDamageTakenPerBattle": 238.95,
        "averageFirstAttackMs": 762.5,
        "averageLifetimeMs": 1749.1482159051818,
        "zeroDamageBattleRate": 0,
        "survivalRate": 0.95,
        "ownerWinRate": 0.1,
        "adoptionRate": 0.8,
        "subUnitBattleAppearances": 20,
        "subUnitMatchesPresent": 4,
        "subUnitAdoptionRate": 0.8
      },
      {
        "unitId": "okina",
        "unitType": "okina",
        "unitName": "隠岐奈",
        "battleAppearances": 48,
        "matchesPresent": 4,
        "averageStarLevel": 1,
        "averageDamagePerBattle": 65.625,
        "averageDamagePerMatch": 630,
        "activeBattleRate": 1,
        "averageAttackCountPerBattle": 2.4583333333333335,
        "averageHitCountPerBattle": 2.4583333333333335,
        "averageDamageTakenPerBattle": 101.625,
        "averageFirstAttackMs": 119.04761904761905,
        "averageLifetimeMs": 2954.848749620505,
        "zeroDamageBattleRate": 0,
        "survivalRate": 0.9583333333333334,
        "ownerWinRate": 0,
        "adoptionRate": 0.8,
        "subUnitBattleAppearances": 0,
        "subUnitMatchesPresent": 0,
        "subUnitAdoptionRate": 0
      },
      {
        "unitId": "sekibanki",
        "unitType": "sekibanki",
        "unitName": "赤蛮奇",
        "battleAppearances": 20,
        "matchesPresent": 4,
        "averageStarLevel": 1,
        "averageDamagePerBattle": 120.4,
        "averageDamagePerMatch": 481.6,
        "activeBattleRate": 0.8,
        "averageAttackCountPerBattle": 1.25,
        "averageHitCountPerBattle": 1.65,
        "averageDamageTakenPerBattle": 219.85,
        "averageFirstAttackMs": 931.8181818181818,
        "averageLifetimeMs": 1872.9074099648872,
        "zeroDamageBattleRate": 0.2,
        "survivalRate": 0.8,
        "ownerWinRate": 0.45,
        "adoptionRate": 0.8,
        "subUnitBattleAppearances": 20,
        "subUnitMatchesPresent": 4,
        "subUnitAdoptionRate": 0.8
      },
      {
        "unitId": "ichirin",
        "unitType": "ichirin",
        "unitName": "雲居一輪＆雲山",
        "battleAppearances": 16,
        "matchesPresent": 4,
        "averageStarLevel": 1,
        "averageDamagePerBattle": 58.8125,
        "averageDamagePerMatch": 188.2,
        "activeBattleRate": 0.875,
        "averageAttackCountPerBattle": 1.3125,
        "averageHitCountPerBattle": 1.3125,
        "averageDamageTakenPerBattle": 100.5,
        "averageFirstAttackMs": 732.1428571428571,
        "averageLifetimeMs": 1658.3638938031356,
        "zeroDamageBattleRate": 0.125,
        "survivalRate": 0.9375,
        "ownerWinRate": 0.5,
        "adoptionRate": 0.8,
        "subUnitBattleAppearances": 15,
        "subUnitMatchesPresent": 4,
        "subUnitAdoptionRate": 0.8
      },
      {
        "unitId": "wakasagihime",
        "unitType": "wakasagihime",
        "unitName": "わかさぎ姫",
        "battleAppearances": 7,
        "matchesPresent": 4,
        "averageStarLevel": 1.4285714285714286,
        "averageDamagePerBattle": 123,
        "averageDamagePerMatch": 172.2,
        "activeBattleRate": 0.8571428571428571,
        "averageAttackCountPerBattle": 2,
        "averageHitCountPerBattle": 2.142857142857143,
        "averageDamageTakenPerBattle": 33,
        "averageFirstAttackMs": 333.3333333333333,
        "averageLifetimeMs": 1878.4362229740382,
        "zeroDamageBattleRate": 0.14285714285714285,
        "survivalRate": 1,
        "ownerWinRate": 0.2857142857142857,
        "adoptionRate": 0.8,
        "subUnitBattleAppearances": 2,
        "subUnitMatchesPresent": 1,
        "subUnitAdoptionRate": 0.2
      },
      {
        "unitId": "nazrin",
        "unitType": "nazrin",
        "unitName": "ナズーリン",
        "battleAppearances": 7,
        "matchesPresent": 4,
        "averageStarLevel": 1.8571428571428572,
        "averageDamagePerBattle": 111.57142857142857,
        "averageDamagePerMatch": 156.2,
        "activeBattleRate": 1,
        "averageAttackCountPerBattle": 1.8571428571428572,
        "averageHitCountPerBattle": 2,
        "averageDamageTakenPerBattle": 40.714285714285715,
        "averageFirstAttackMs": 451.12781954887225,
        "averageLifetimeMs": 2003.6681339202348,
        "zeroDamageBattleRate": 0,
        "survivalRate": 1,
        "ownerWinRate": 0.2857142857142857,
        "adoptionRate": 0.8,
        "subUnitBattleAppearances": 3,
        "subUnitMatchesPresent": 2,
        "subUnitAdoptionRate": 0.4
      },
      {
        "unitId": "marisa",
        "unitType": "marisa",
        "unitName": "魔理沙",
        "battleAppearances": 36,
        "matchesPresent": 3,
        "averageStarLevel": 1,
        "averageDamagePerBattle": 1705.4166666666667,
        "averageDamagePerMatch": 12279,
        "activeBattleRate": 0.6944444444444444,
        "averageAttackCountPerBattle": 1.0833333333333333,
        "averageHitCountPerBattle": 7.722222222222222,
        "averageDamageTakenPerBattle": 95.11111111111111,
        "averageFirstAttackMs": 1000,
        "averageLifetimeMs": 1651.293762232875,
        "zeroDamageBattleRate": 0,
        "survivalRate": 0.8888888888888888,
        "ownerWinRate": 0.6666666666666666,
        "adoptionRate": 0.6,
        "subUnitBattleAppearances": 0,
        "subUnitMatchesPresent": 0,
        "subUnitAdoptionRate": 0
      },
      {
        "unitId": "byakuren",
        "unitType": "byakuren",
        "unitName": "聖白蓮",
        "battleAppearances": 8,
        "matchesPresent": 3,
        "averageStarLevel": 1,
        "averageDamagePerBattle": 261.75,
        "averageDamagePerMatch": 418.8,
        "activeBattleRate": 1,
        "averageAttackCountPerBattle": 2.625,
        "averageHitCountPerBattle": 2.625,
        "averageDamageTakenPerBattle": 408.375,
        "averageFirstAttackMs": 1000,
        "averageLifetimeMs": 3156.3467492260065,
        "zeroDamageBattleRate": 0,
        "survivalRate": 1,
        "ownerWinRate": 0,
        "adoptionRate": 0.6,
        "subUnitBattleAppearances": 8,
        "subUnitMatchesPresent": 3,
        "subUnitAdoptionRate": 0.6
      },
      {
        "unitId": "reimu",
        "unitType": "reimu",
        "unitName": "霊夢",
        "battleAppearances": 36,
        "matchesPresent": 3,
        "averageStarLevel": 1,
        "averageDamagePerBattle": 9.027777777777779,
        "averageDamagePerMatch": 65,
        "activeBattleRate": 0.19444444444444445,
        "averageAttackCountPerBattle": 0.6388888888888888,
        "averageHitCountPerBattle": 0.6388888888888888,
        "averageDamageTakenPerBattle": 100.58333333333333,
        "averageFirstAttackMs": 4011.904761904762,
        "averageLifetimeMs": 3385.0026010758725,
        "zeroDamageBattleRate": 0.8055555555555556,
        "survivalRate": 1,
        "ownerWinRate": 1,
        "adoptionRate": 0.6,
        "subUnitBattleAppearances": 0,
        "subUnitMatchesPresent": 0,
        "subUnitAdoptionRate": 0
      },
      {
        "unitId": "koishi",
        "unitType": "koishi",
        "unitName": "古明地こいし",
        "battleAppearances": 5,
        "matchesPresent": 2,
        "averageStarLevel": 1,
        "averageDamagePerBattle": 289.6,
        "averageDamagePerMatch": 289.6,
        "activeBattleRate": 0.8,
        "averageAttackCountPerBattle": 2,
        "averageHitCountPerBattle": 2.8,
        "averageDamageTakenPerBattle": 338.2,
        "averageFirstAttackMs": 750,
        "averageLifetimeMs": 2248.1089086352245,
        "zeroDamageBattleRate": 0.2,
        "survivalRate": 0.8,
        "ownerWinRate": 0.2,
        "adoptionRate": 0.4,
        "subUnitBattleAppearances": 4,
        "subUnitMatchesPresent": 2,
        "subUnitAdoptionRate": 0.4
      },
      {
        "unitId": "shou",
        "unitType": "shou",
        "unitName": "寅丸星",
        "battleAppearances": 2,
        "matchesPresent": 2,
        "averageStarLevel": 1,
        "averageDamagePerBattle": 579.5,
        "averageDamagePerMatch": 231.8,
        "activeBattleRate": 1,
        "averageAttackCountPerBattle": 2,
        "averageHitCountPerBattle": 5.5,
        "averageDamageTakenPerBattle": 31,
        "averageFirstAttackMs": 526.3157894736843,
        "averageLifetimeMs": 1732.0261437908498,
        "zeroDamageBattleRate": 0,
        "survivalRate": 1,
        "ownerWinRate": 0,
        "adoptionRate": 0.4,
        "subUnitBattleAppearances": 2,
        "subUnitMatchesPresent": 2,
        "subUnitAdoptionRate": 0.4
      },
      {
        "unitId": "megumu",
        "unitType": "megumu",
        "unitName": "飯綱丸龍",
        "battleAppearances": 3,
        "matchesPresent": 2,
        "averageStarLevel": 1,
        "averageDamagePerBattle": 241.66666666666666,
        "averageDamagePerMatch": 145,
        "activeBattleRate": 0.6666666666666666,
        "averageAttackCountPerBattle": 2.6666666666666665,
        "averageHitCountPerBattle": 3.3333333333333335,
        "averageDamageTakenPerBattle": 77,
        "averageFirstAttackMs": 952.3809523809523,
        "averageLifetimeMs": 2992.105933282404,
        "zeroDamageBattleRate": 0.3333333333333333,
        "survivalRate": 1,
        "ownerWinRate": 0.3333333333333333,
        "adoptionRate": 0.4,
        "subUnitBattleAppearances": 3,
        "subUnitMatchesPresent": 2,
        "subUnitAdoptionRate": 0.4
      },
      {
        "unitId": "tsukasa",
        "unitType": "tsukasa",
        "unitName": "菅牧典",
        "battleAppearances": 1,
        "matchesPresent": 1,
        "averageStarLevel": 1,
        "averageDamagePerBattle": 102,
        "averageDamagePerMatch": 20.4,
        "activeBattleRate": 1,
        "averageAttackCountPerBattle": 2,
        "averageHitCountPerBattle": 2,
        "averageDamageTakenPerBattle": 0,
        "averageFirstAttackMs": 0,
        "averageLifetimeMs": 2000,
        "zeroDamageBattleRate": 0,
        "survivalRate": 1,
        "ownerWinRate": 0,
        "adoptionRate": 0.2,
        "subUnitBattleAppearances": 1,
        "subUnitMatchesPresent": 1,
        "subUnitAdoptionRate": 0.2
      },
      {
        "unitId": "tojiko",
        "unitType": "tojiko",
        "unitName": "蘇我屠自古",
        "battleAppearances": 1,
        "matchesPresent": 1,
        "averageStarLevel": 1,
        "averageDamagePerBattle": 64,
        "averageDamagePerMatch": 12.8,
        "activeBattleRate": 1,
        "averageAttackCountPerBattle": 1,
        "averageHitCountPerBattle": 1,
        "averageDamageTakenPerBattle": 0,
        "averageFirstAttackMs": 2857.142857142857,
        "averageLifetimeMs": 3000,
        "zeroDamageBattleRate": 0,
        "survivalRate": 1,
        "ownerWinRate": 1,
        "adoptionRate": 0.2,
        "subUnitBattleAppearances": 0,
        "subUnitMatchesPresent": 0,
        "subUnitAdoptionRate": 0
      },
      {
        "unitId": "murasa",
        "unitType": "murasa",
        "unitName": "村紗水蜜",
        "battleAppearances": 1,
        "matchesPresent": 1,
        "averageStarLevel": 1,
        "averageDamagePerBattle": 62,
        "averageDamagePerMatch": 12.4,
        "activeBattleRate": 1,
        "averageAttackCountPerBattle": 1,
        "averageHitCountPerBattle": 1,
        "averageDamageTakenPerBattle": 0,
        "averageFirstAttackMs": 0,
        "averageLifetimeMs": 909.090909090909,
        "zeroDamageBattleRate": 0,
        "survivalRate": 1,
        "ownerWinRate": 0,
        "adoptionRate": 0.2,
        "subUnitBattleAppearances": 1,
        "subUnitMatchesPresent": 1,
        "subUnitAdoptionRate": 0.2
      }
    ],
    "finalBoardUnitMetrics": [
      {
        "unitId": "yoshika",
        "unitType": "vanguard",
        "unitName": "宮古芳香",
        "totalCopies": 10,
        "matchesPresent": 5,
        "averageCopiesPerMatch": 2,
        "adoptionRate": 1
      },
      {
        "unitId": "rin",
        "unitType": "vanguard",
        "unitName": "火焔猫燐",
        "totalCopies": 7,
        "matchesPresent": 5,
        "averageCopiesPerMatch": 1.4,
        "adoptionRate": 1
      },
      {
        "unitId": "kagerou",
        "unitType": "vanguard",
        "unitName": "今泉影狼",
        "totalCopies": 5,
        "matchesPresent": 5,
        "averageCopiesPerMatch": 1,
        "adoptionRate": 1
      },
      {
        "unitId": "byakuren",
        "unitType": "vanguard",
        "unitName": "聖白蓮",
        "totalCopies": 8,
        "matchesPresent": 4,
        "averageCopiesPerMatch": 1.6,
        "adoptionRate": 0.8
      },
      {
        "unitId": "momoyo",
        "unitType": "vanguard",
        "unitName": "姫虫百々世",
        "totalCopies": 4,
        "matchesPresent": 4,
        "averageCopiesPerMatch": 0.8,
        "adoptionRate": 0.8
      },
      {
        "unitId": "patchouli",
        "unitType": "mage",
        "unitName": "パチュリー・ノーレッジ",
        "totalCopies": 4,
        "matchesPresent": 4,
        "averageCopiesPerMatch": 0.8,
        "adoptionRate": 0.8
      },
      {
        "unitId": "hecatia",
        "unitType": "mage",
        "unitName": "ヘカーティア・ラピスラズリ",
        "totalCopies": 3,
        "matchesPresent": 3,
        "averageCopiesPerMatch": 0.6,
        "adoptionRate": 0.6
      },
      {
        "unitId": "nazrin",
        "unitType": "ranger",
        "unitName": "ナズーリン",
        "totalCopies": 3,
        "matchesPresent": 3,
        "averageCopiesPerMatch": 0.6,
        "adoptionRate": 0.6
      },
      {
        "unitId": "seiga",
        "unitType": "assassin",
        "unitName": "霍青娥",
        "totalCopies": 3,
        "matchesPresent": 2,
        "averageCopiesPerMatch": 0.6,
        "adoptionRate": 0.4
      },
      {
        "unitId": "chimata",
        "unitType": "mage",
        "unitName": "天弓千亦",
        "totalCopies": 2,
        "matchesPresent": 2,
        "averageCopiesPerMatch": 0.4,
        "adoptionRate": 0.4
      },
      {
        "unitId": "clownpiece",
        "unitType": "ranger",
        "unitName": "クラウンピース",
        "totalCopies": 2,
        "matchesPresent": 2,
        "averageCopiesPerMatch": 0.4,
        "adoptionRate": 0.4
      },
      {
        "unitId": "sekibanki",
        "unitType": "assassin",
        "unitName": "赤蛮奇",
        "totalCopies": 2,
        "matchesPresent": 2,
        "averageCopiesPerMatch": 0.4,
        "adoptionRate": 0.4
      },
      {
        "unitId": "shou",
        "unitType": "mage",
        "unitName": "寅丸星",
        "totalCopies": 2,
        "matchesPresent": 2,
        "averageCopiesPerMatch": 0.4,
        "adoptionRate": 0.4
      },
      {
        "unitId": "megumu",
        "unitType": "ranger",
        "unitName": "飯綱丸龍",
        "totalCopies": 1,
        "matchesPresent": 1,
        "averageCopiesPerMatch": 0.2,
        "adoptionRate": 0.2
      },
      {
        "unitId": "sakuya",
        "unitType": "assassin",
        "unitName": "十六夜咲夜",
        "totalCopies": 1,
        "matchesPresent": 1,
        "averageCopiesPerMatch": 0.2,
        "adoptionRate": 0.2
      },
      {
        "unitId": "satori",
        "unitType": "mage",
        "unitName": "古明地さとり",
        "totalCopies": 1,
        "matchesPresent": 1,
        "averageCopiesPerMatch": 0.2,
        "adoptionRate": 0.2
      },
      {
        "unitId": "wakasagihime",
        "unitType": "ranger",
        "unitName": "わかさぎ姫",
        "totalCopies": 1,
        "matchesPresent": 1,
        "averageCopiesPerMatch": 0.2,
        "adoptionRate": 0.2
      },
      {
        "unitId": "zanmu",
        "unitType": "mage",
        "unitName": "日白残無",
        "totalCopies": 1,
        "matchesPresent": 1,
        "averageCopiesPerMatch": 0.2,
        "adoptionRate": 0.2
      }
    ],
    "topDamageUnits": [
      {
        "unitId": "marisa",
        "unitName": "魔理沙",
        "side": "raid",
        "totalDamage": 61395,
        "appearances": 3,
        "averageDamagePerMatch": 12279
      },
      {
        "unitId": "patchouli",
        "unitName": "patchouli",
        "side": "boss",
        "totalDamage": 30830,
        "appearances": 5,
        "averageDamagePerMatch": 6166
      },
      {
        "unitId": "yoshika",
        "unitName": "宮古芳香",
        "side": "raid",
        "totalDamage": 14502,
        "appearances": 5,
        "averageDamagePerMatch": 2900.4
      },
      {
        "unitId": "rin",
        "unitName": "火焔猫燐",
        "side": "raid",
        "totalDamage": 11781,
        "appearances": 5,
        "averageDamagePerMatch": 2356.2
      },
      {
        "unitId": "sakuya",
        "unitName": "sakuya",
        "side": "boss",
        "totalDamage": 8973,
        "appearances": 5,
        "averageDamagePerMatch": 1794.6
      },
      {
        "unitId": "hecatia",
        "unitName": "hecatia",
        "side": "boss",
        "totalDamage": 8019,
        "appearances": 3,
        "averageDamagePerMatch": 1603.8
      },
      {
        "unitId": "nazrin",
        "unitName": "nazrin",
        "side": "boss",
        "totalDamage": 6050,
        "appearances": 4,
        "averageDamagePerMatch": 1210
      },
      {
        "unitId": "clownpiece",
        "unitName": "clownpiece",
        "side": "boss",
        "totalDamage": 5245,
        "appearances": 2,
        "averageDamagePerMatch": 1049
      },
      {
        "unitId": "remilia",
        "unitName": "レミリア",
        "side": "boss",
        "totalDamage": 5061,
        "appearances": 5,
        "averageDamagePerMatch": 1012.2
      },
      {
        "unitId": "yoshika",
        "unitName": "yoshika",
        "side": "boss",
        "totalDamage": 4975,
        "appearances": 5,
        "averageDamagePerMatch": 995
      }
    ],
    "highCostSummary": {
      "offerObservationCount": 517,
      "offerMatchCount": 5,
      "purchaseCount": 179,
      "purchaseMatchCount": 5,
      "finalBoardCopies": 16,
      "finalBoardMatchCount": 5,
      "finalBoardAdoptionRate": 1
    },
    "highCostOfferMetrics": [
      {
        "unitId": "shou",
        "unitName": "寅丸星",
        "unitType": "mage",
        "role": "raid",
        "source": "shop",
        "cost": 4,
        "observationCount": 58,
        "matchesPresent": 5,
        "offeredMatchRate": 1
      },
      {
        "unitId": "junko",
        "unitName": "純狐",
        "unitType": "vanguard",
        "role": "raid",
        "source": "shop",
        "cost": 4,
        "observationCount": 56,
        "matchesPresent": 5,
        "offeredMatchRate": 1
      },
      {
        "unitId": "futo",
        "unitName": "物部布都",
        "unitType": "mage",
        "role": "raid",
        "source": "shop",
        "cost": 4,
        "observationCount": 54,
        "matchesPresent": 5,
        "offeredMatchRate": 1
      },
      {
        "unitId": "utsuho",
        "unitName": "霊烏路空",
        "unitType": "mage",
        "role": "raid",
        "source": "shop",
        "cost": 4,
        "observationCount": 51,
        "matchesPresent": 5,
        "offeredMatchRate": 1
      },
      {
        "unitId": "chimata",
        "unitName": "天弓千亦",
        "unitType": "mage",
        "role": "raid",
        "source": "shop",
        "cost": 4,
        "observationCount": 48,
        "matchesPresent": 5,
        "offeredMatchRate": 1
      },
      {
        "unitId": "patchouli",
        "unitName": "パチュリー・ノーレッジ",
        "unitType": "mage",
        "role": "boss",
        "source": "bossShop",
        "cost": 4,
        "observationCount": 40,
        "matchesPresent": 5,
        "offeredMatchRate": 1
      },
      {
        "unitId": "zanmu",
        "unitName": "日白残無",
        "unitType": "mage",
        "role": "raid",
        "source": "shop",
        "cost": 5,
        "observationCount": 34,
        "matchesPresent": 5,
        "offeredMatchRate": 1
      },
      {
        "unitId": "hecatia",
        "unitName": "ヘカーティア・ラピスラズリ",
        "unitType": "mage",
        "role": "raid",
        "source": "shop",
        "cost": 5,
        "observationCount": 33,
        "matchesPresent": 5,
        "offeredMatchRate": 1
      },
      {
        "unitId": "byakuren",
        "unitName": "聖白蓮",
        "unitType": "vanguard",
        "role": "raid",
        "source": "shop",
        "cost": 5,
        "observationCount": 22,
        "matchesPresent": 5,
        "offeredMatchRate": 1
      },
      {
        "unitId": "miko",
        "unitName": "豊聡耳神子",
        "unitType": "mage",
        "role": "raid",
        "source": "shop",
        "cost": 5,
        "observationCount": 21,
        "matchesPresent": 5,
        "offeredMatchRate": 1
      },
      {
        "unitId": "futo",
        "unitName": "物部布都",
        "unitType": "mage",
        "role": "boss",
        "source": "shop",
        "cost": 4,
        "observationCount": 19,
        "matchesPresent": 5,
        "offeredMatchRate": 1
      },
      {
        "unitId": "shou",
        "unitName": "寅丸星",
        "unitType": "mage",
        "role": "boss",
        "source": "shop",
        "cost": 4,
        "observationCount": 17,
        "matchesPresent": 5,
        "offeredMatchRate": 1
      },
      {
        "unitId": "junko",
        "unitName": "純狐",
        "unitType": "vanguard",
        "role": "boss",
        "source": "shop",
        "cost": 4,
        "observationCount": 13,
        "matchesPresent": 5,
        "offeredMatchRate": 1
      },
      {
        "unitId": "hecatia",
        "unitName": "ヘカーティア・ラピスラズリ",
        "unitType": "mage",
        "role": "boss",
        "source": "shop",
        "cost": 5,
        "observationCount": 11,
        "matchesPresent": 5,
        "offeredMatchRate": 1
      },
      {
        "unitId": "utsuho",
        "unitName": "霊烏路空",
        "unitType": "mage",
        "role": "boss",
        "source": "shop",
        "cost": 4,
        "observationCount": 11,
        "matchesPresent": 5,
        "offeredMatchRate": 1
      },
      {
        "unitId": "chimata",
        "unitName": "天弓千亦",
        "unitType": "mage",
        "role": "boss",
        "source": "shop",
        "cost": 4,
        "observationCount": 12,
        "matchesPresent": 4,
        "offeredMatchRate": 0.8
      },
      {
        "unitId": "byakuren",
        "unitName": "聖白蓮",
        "unitType": "vanguard",
        "role": "boss",
        "source": "shop",
        "cost": 5,
        "observationCount": 8,
        "matchesPresent": 4,
        "offeredMatchRate": 0.8
      },
      {
        "unitId": "zanmu",
        "unitName": "日白残無",
        "unitType": "mage",
        "role": "boss",
        "source": "shop",
        "cost": 5,
        "observationCount": 4,
        "matchesPresent": 4,
        "offeredMatchRate": 0.8
      },
      {
        "unitId": "miko",
        "unitName": "豊聡耳神子",
        "unitType": "mage",
        "role": "boss",
        "source": "shop",
        "cost": 5,
        "observationCount": 5,
        "matchesPresent": 3,
        "offeredMatchRate": 0.6
      }
    ],
    "rangeDamageEfficiencyMetrics": [
      {
        "side": "boss",
        "rangeBand": "range_1",
        "battleAppearances": 157,
        "totalDamage": 22161,
        "totalTheoreticalBaseDamage": 28895.797547344304,
        "normalizedDamageEfficiency": 0.7669281307667775,
        "totalAttackCount": 502,
        "totalTheoreticalAttackCount": 426.8819661676471,
        "attackOpportunityUtilization": 1.1759690963446607,
        "averageDamagePerBattle": 141.15286624203821,
        "averageFirstAttackMs": 11.146496815286625,
        "firstAttackSamples": 157,
        "zeroDamageBattleRate": 0
      },
      {
        "side": "boss",
        "rangeBand": "range_2_plus",
        "battleAppearances": 232,
        "totalDamage": 86101,
        "totalTheoreticalBaseDamage": 34992.60467821736,
        "normalizedDamageEfficiency": 2.4605484727919453,
        "totalAttackCount": 592,
        "totalTheoreticalAttackCount": 491.1684232417048,
        "attackOpportunityUtilization": 1.205289208318418,
        "averageDamagePerBattle": 371.125,
        "averageFirstAttackMs": 84.61106798791654,
        "firstAttackSamples": 227,
        "zeroDamageBattleRate": 0.021551724137931036
      },
      {
        "side": "raid",
        "rangeBand": "range_1",
        "battleAppearances": 431,
        "totalDamage": 46773,
        "totalTheoreticalBaseDamage": 64245.43329558791,
        "normalizedDamageEfficiency": 0.7280361825065652,
        "totalAttackCount": 801,
        "totalTheoreticalAttackCount": 970.1416116339063,
        "attackOpportunityUtilization": 0.8256526577093842,
        "averageDamagePerBattle": 108.52204176334106,
        "averageFirstAttackMs": 635.8786132324942,
        "firstAttackSamples": 313,
        "zeroDamageBattleRate": 0.2737819025522042
      },
      {
        "side": "raid",
        "rangeBand": "range_2_plus",
        "battleAppearances": 106,
        "totalDamage": 68299,
        "totalTheoreticalBaseDamage": 11780.38023757663,
        "normalizedDamageEfficiency": 5.797690619708719,
        "totalAttackCount": 200,
        "totalTheoreticalAttackCount": 203.83255980569896,
        "attackOpportunityUtilization": 0.9811975093216103,
        "averageDamagePerBattle": 644.3301886792453,
        "averageFirstAttackMs": 448.2442665804296,
        "firstAttackSamples": 93,
        "zeroDamageBattleRate": 0.018867924528301886
      }
    ],
    "rangeActionDiagnosticsMetrics": [
      {
        "side": "boss",
        "rangeBand": "range_1",
        "battleAppearances": 157,
        "movedBattleRate": 0.10828025477707007,
        "averageMoveCountPerBattle": 0.10828025477707007,
        "averageFirstMoveMs": 1794.1176470588234,
        "firstMoveSamples": 17,
        "averageMoveToFirstAttackMs": 250,
        "moveToFirstAttackSamples": 7,
        "repositionBattleRate": 0.06369426751592357,
        "averageRepositionMoveCountPerBattle": 0.06369426751592357,
        "reachedAttackRangeBattleRate": 1,
        "noAttackDespiteReachingRangeBattleRate": 0,
        "noAttackWithoutReachingRangeBattleRate": 0,
        "averageInitialNearestEnemyDistance": 1.0445859872611465,
        "averageBestNearestEnemyDistance": 1,
        "averageDistanceClosed": 0.044585987261146494,
        "noAttackBattleRate": 0,
        "movedNoAttackBattleRate": 0,
        "attackedNoHitBattleRate": 0,
        "lateSingleAttackBattleRate": 0,
        "moveTargetDiagnosticSampleCount": 17,
        "suboptimalMoveTargetRate": 0,
        "averageExcessApproachSteps": 0,
        "averageOutsideAttackRangeBeforeFirstAttackMs": 0,
        "averageInAttackRangeBeforeFirstAttackMs": 11.146496815286625,
        "averageAfterFirstAttackMs": 3056.642779217759,
        "averageFirstReachedAttackRangeAtMs": 0,
        "firstReachedAttackRangeSamples": 7
      },
      {
        "side": "boss",
        "rangeBand": "range_2_plus",
        "battleAppearances": 232,
        "movedBattleRate": 0.09482758620689655,
        "averageMoveCountPerBattle": 0.09913793103448276,
        "averageFirstMoveMs": 363.6363636363636,
        "firstMoveSamples": 22,
        "averageMoveToFirstAttackMs": 1200.419527078566,
        "moveToFirstAttackSamples": 16,
        "repositionBattleRate": 0.004310344827586207,
        "averageRepositionMoveCountPerBattle": 0.004310344827586207,
        "reachedAttackRangeBattleRate": 1,
        "noAttackDespiteReachingRangeBattleRate": 0.021551724137931036,
        "noAttackWithoutReachingRangeBattleRate": 0,
        "averageInitialNearestEnemyDistance": 2.7629310344827585,
        "averageBestNearestEnemyDistance": 1.9698275862068966,
        "averageDistanceClosed": 0.7931034482758621,
        "noAttackBattleRate": 0.021551724137931036,
        "movedNoAttackBattleRate": 0.021551724137931036,
        "attackedNoHitBattleRate": 0,
        "lateSingleAttackBattleRate": 0.02586206896551724,
        "moveTargetDiagnosticSampleCount": 23,
        "suboptimalMoveTargetRate": 0,
        "averageExcessApproachSteps": 0,
        "averageOutsideAttackRangeBeforeFirstAttackMs": 4.310344827586207,
        "averageInAttackRangeBeforeFirstAttackMs": 99.31365201427539,
        "averageAfterFirstAttackMs": 2384.6638105816087,
        "averageFirstReachedAttackRangeAtMs": 47.61904761904762,
        "firstReachedAttackRangeSamples": 21
      },
      {
        "side": "raid",
        "rangeBand": "range_1",
        "battleAppearances": 431,
        "movedBattleRate": 0.6380510440835266,
        "averageMoveCountPerBattle": 1.7795823665893271,
        "averageFirstMoveMs": 0,
        "firstMoveSamples": 275,
        "averageMoveToFirstAttackMs": 1239.451476793249,
        "moveToFirstAttackSamples": 158,
        "repositionBattleRate": 0,
        "averageRepositionMoveCountPerBattle": 0,
        "reachedAttackRangeBattleRate": 0.7517401392111369,
        "noAttackDespiteReachingRangeBattleRate": 0.025522041763341066,
        "noAttackWithoutReachingRangeBattleRate": 0.2482598607888631,
        "averageInitialNearestEnemyDistance": 2.577726218097448,
        "averageBestNearestEnemyDistance": 1.3271461716937354,
        "averageDistanceClosed": 1.2505800464037122,
        "noAttackBattleRate": 0.2737819025522042,
        "movedNoAttackBattleRate": 0.271461716937355,
        "attackedNoHitBattleRate": 0,
        "lateSingleAttackBattleRate": 0.08584686774941995,
        "moveTargetDiagnosticSampleCount": 767,
        "suboptimalMoveTargetRate": 0,
        "averageExcessApproachSteps": 0,
        "averageOutsideAttackRangeBeforeFirstAttackMs": 933.6964739603139,
        "averageInAttackRangeBeforeFirstAttackMs": 107.93903036186441,
        "averageAfterFirstAttackMs": 1633.6741038481316,
        "averageFirstReachedAttackRangeAtMs": 991.2790697674419,
        "firstReachedAttackRangeSamples": 172
      },
      {
        "side": "raid",
        "rangeBand": "range_2_plus",
        "battleAppearances": 106,
        "movedBattleRate": 0.3018867924528302,
        "averageMoveCountPerBattle": 0.5188679245283019,
        "averageFirstMoveMs": 0,
        "firstMoveSamples": 32,
        "averageMoveToFirstAttackMs": 1691.228070175439,
        "moveToFirstAttackSamples": 20,
        "repositionBattleRate": 0,
        "averageRepositionMoveCountPerBattle": 0,
        "reachedAttackRangeBattleRate": 0.9622641509433962,
        "noAttackDespiteReachingRangeBattleRate": 0.08490566037735849,
        "noAttackWithoutReachingRangeBattleRate": 0.03773584905660377,
        "averageInitialNearestEnemyDistance": 4.40566037735849,
        "averageBestNearestEnemyDistance": 3.707547169811321,
        "averageDistanceClosed": 0.6981132075471698,
        "noAttackBattleRate": 0.12264150943396226,
        "movedNoAttackBattleRate": 0.11320754716981132,
        "attackedNoHitBattleRate": 0,
        "lateSingleAttackBattleRate": 0.1320754716981132,
        "moveTargetDiagnosticSampleCount": 55,
        "suboptimalMoveTargetRate": 0,
        "averageExcessApproachSteps": 0,
        "averageOutsideAttackRangeBeforeFirstAttackMs": 252.92003593890385,
        "averageInAttackRangeBeforeFirstAttackMs": 285.0348785055836,
        "averageAfterFirstAttackMs": 1790.3800564701119,
        "averageFirstReachedAttackRangeAtMs": 638.8888888888889,
        "firstReachedAttackRangeSamples": 36
      }
    ],
    "rangeFormationDiagnosticsMetrics": [
      {
        "side": "boss",
        "rangeBand": "range_1",
        "battleAppearances": 157,
        "frontAllyBlockedBattleRate": 0,
        "averageFrontAllyCount": 0,
        "averageInitialRow": 2,
        "averageInitialColumn": 2.656050955414013,
        "zeroDamageBattleRateWithFrontAlly": null,
        "zeroDamageBattleRateWithoutFrontAlly": 0,
        "noAttackBattleRateWithFrontAlly": null,
        "noAttackBattleRateWithoutFrontAlly": 0
      },
      {
        "side": "boss",
        "rangeBand": "range_2_plus",
        "battleAppearances": 232,
        "frontAllyBlockedBattleRate": 0.7974137931034483,
        "averageFrontAllyCount": 1.0862068965517242,
        "averageInitialRow": 0.30603448275862066,
        "averageInitialColumn": 2.5129310344827585,
        "zeroDamageBattleRateWithFrontAlly": 0.005405405405405406,
        "zeroDamageBattleRateWithoutFrontAlly": 0.0851063829787234,
        "noAttackBattleRateWithFrontAlly": 0.005405405405405406,
        "noAttackBattleRateWithoutFrontAlly": 0.0851063829787234
      },
      {
        "side": "raid",
        "rangeBand": "range_1",
        "battleAppearances": 431,
        "frontAllyBlockedBattleRate": 0.1925754060324826,
        "averageFrontAllyCount": 0.1925754060324826,
        "averageInitialRow": 3.445475638051044,
        "averageInitialColumn": 2.5243619489559164,
        "zeroDamageBattleRateWithFrontAlly": 0.9036144578313253,
        "zeroDamageBattleRateWithoutFrontAlly": 0.1235632183908046,
        "noAttackBattleRateWithFrontAlly": 0.9036144578313253,
        "noAttackBattleRateWithoutFrontAlly": 0.1235632183908046
      },
      {
        "side": "raid",
        "rangeBand": "range_2_plus",
        "battleAppearances": 106,
        "frontAllyBlockedBattleRate": 0.7075471698113207,
        "averageFrontAllyCount": 0.7075471698113207,
        "averageInitialRow": 4.971698113207547,
        "averageInitialColumn": 1.5849056603773586,
        "zeroDamageBattleRateWithFrontAlly": 0,
        "zeroDamageBattleRateWithoutFrontAlly": 0.06451612903225806,
        "noAttackBattleRateWithFrontAlly": 0.14666666666666667,
        "noAttackBattleRateWithoutFrontAlly": 0.06451612903225806
      }
    ],
    "metadata": {
      "mode": "custom",
      "timeScale": 0.01,
      "timings": {
        "readyAutoStartMs": 200,
        "prepDurationMs": 900,
        "battleDurationMs": 800,
        "settleDurationMs": 20,
        "eliminationDurationMs": 10,
        "selectionTimeoutMs": 200
      }
    }
  },
  "failures": [],
  "startedAt": "2026-04-11T10:39:20.024Z",
  "finishedAt": "2026-04-11T10:40:25.808Z",
  "durationMs": 65784,
  "logPath": "C:\\Users\\kou-1\\Dev_Workspace\\00_Source_Codes\\auto-chess-mvp\\.tmp\\bot-balance-baseline\\run-2026-04-11-100-range-balance-spacing-v1\\chunk-005.log"
}
